diffpy/__init__.py
diffpy/pdfmorph/__init__.py
diffpy/pdfmorph/log.py
diffpy/pdfmorph/pdfmorph_api.py
diffpy/pdfmorph/pdfmorph_io.py
diffpy/pdfmorph/pdfmorphapp.py
diffpy/pdfmorph/pdfplot.py
diffpy/pdfmorph/refine.py
diffpy/pdfmorph/tools.py
diffpy/pdfmorph/version.py
diffpy/pdfmorph/morph_helpers/__init__.py
diffpy/pdfmorph/morph_helpers/transformpdftordf.py
diffpy/pdfmorph/morph_helpers/transformrdftopdf.py
diffpy/pdfmorph/morphs/__init__.py
diffpy/pdfmorph/morphs/morph.py
diffpy/pdfmorph/morphs/morphchain.py
diffpy/pdfmorph/morphs/morphishape.py
diffpy/pdfmorph/morphs/morphresolution.py
diffpy/pdfmorph/morphs/morphrgrid.py
diffpy/pdfmorph/morphs/morphscale.py
diffpy/pdfmorph/morphs/morphshape.py
diffpy/pdfmorph/morphs/morphshift.py
diffpy/pdfmorph/morphs/morphsmear.py
diffpy/pdfmorph/morphs/morphstretch.py
diffpy.pdfmorph-0.1.3.dist-info/AUTHORS.rst
diffpy.pdfmorph-0.1.3.dist-info/LICENSE.rst
diffpy.pdfmorph-0.1.3.dist-info/METADATA
diffpy.pdfmorph-0.1.3.dist-info/WHEEL
diffpy.pdfmorph-0.1.3.dist-info/entry_points.txt
diffpy.pdfmorph-0.1.3.dist-info/top_level.txt
diffpy.pdfmorph-0.1.3.dist-info/RECORD
