Metadata-Version: 2.1
Name: diffpy.pdfmorph
Version: 0.1.3
Summary: Tools for manipulating and comparing PDF profiles
Author-email: "Simon J.L. Billinge group" <simon.billinge@gmail.com>
Maintainer-email: "Simon J.L. Billinge group" <simon.billinge@gmail.com>
Project-URL: Homepage, https://github.com/diffpy/diffpy.pdfmorph/
Project-URL: Issues, https://github.com/diffpy/diffpy.pdfmorph/issues/
Keywords: diffpy,pdf,data interpretation
Classifier: Development Status :: 5 - Production/Stable
Classifier: Environment :: Console
Classifier: Intended Audience :: Developers
Classifier: Intended Audience :: Science/Research
Classifier: License :: OSI Approved :: BSD License
Classifier: Operating System :: MacOS :: MacOS X
Classifier: Operating System :: Microsoft :: Windows
Classifier: Operating System :: POSIX
Classifier: Operating System :: Unix
Classifier: Programming Language :: Python :: 3.10
Classifier: Programming Language :: Python :: 3.11
Classifier: Programming Language :: Python :: 3.12
Classifier: Topic :: Scientific/Engineering :: Physics
Classifier: Topic :: Scientific/Engineering :: Chemistry
Requires-Python: >=3.10
License-File: LICENSE.rst
License-File: AUTHORS.rst
Requires-Dist: numpy
Requires-Dist: scipy
Requires-Dist: diffpy.utils
Requires-Dist: matplotlib
Requires-Dist: bg-mpl-stylesheets
